MANIFEST.in
README.md
requirements.txt
setup.cfg
setup.py
versioneer.py
botcity/plugins/aws/lambda_functions/__init__.py
botcity/plugins/aws/lambda_functions/_version.py
botcity/plugins/aws/lambda_functions/plugin.py
botcity_aws_lambda_plugin.egg-info/PKG-INFO
botcity_aws_lambda_plugin.egg-info/SOURCES.txt
botcity_aws_lambda_plugin.egg-info/dependency_links.txt
botcity_aws_lambda_plugin.egg-info/requires.txt
botcity_aws_lambda_plugin.egg-info/top_level.txt